UART_Actuator/led_controller_simulation/led_controller.v
module led_controller (
    input wire clk,               // system clock
    input wire [7:0] rx_byte,     // received UART byte
    input wire rx_done,           // high for 1 cycle when byte received

    output reg led_r,             // Red LED control
    output reg led_g,             // Green LED control
    output reg led_b              // Blue LED control
);

    always @(posedge clk) begin
        if (rx_done) begin
            case (rx_byte)
                // ---- Red LED ----
                8'h52: led_r <= 1'b1;   // 'R' → Red ON
                8'h72: led_r <= 1'b0;   // 'r' → Red OFF

                // ---- Green LED ----
                8'h47: led_g <= 1'b1;   // 'G' → Green ON
                8'h67: led_g <= 1'b0;   // 'g' → Green OFF

                // ---- Blue LED ----
                8'h42: led_b <= 1'b1;   // 'B' → Blue ON
                8'h62: led_b <= 1'b0;   // 'b' → Blue OFF

                default: ; // ignore other bytes
            endcase
        end
    end

endmodule

UART_Actuator/led_controller_simulation/led_controller_tb.v
`timescale 1ns/1ps

module led_controller_tb;

  // Testbench signals
  reg clk;
  reg [7:0] rx_byte;
  reg rx_done;
  wire led_r;
  wire led_g;
  wire led_b;

  // DUT instantiation
  led_controller uut (
    .clk(clk),
    .rx_byte(rx_byte),
    .rx_done(rx_done),
    .led_r(led_r),
    .led_g(led_g),
    .led_b(led_b)
  );

  // Clock generation: 100 MHz
  initial begin
    clk = 0;
    forever #5 clk = ~clk; // 10 ns period
  end

  // VCD dump setup
  initial begin
    $dumpfile("led_controller.vcd");
    $dumpvars(0, led_controller_tb);
  end

  // Stimulus
  initial begin
    $display("===== Starting LED Controller Testbench =====");
    rx_byte = 8'd0;
    rx_done = 0;

    // Wait for global reset
    #20;

    // Test RED ON ('R' = 0x52)
    rx_byte = 8'h52; rx_done = 1; #10; rx_done = 0; #10;
    $display("Sent 'R': led_r=%b (expect 1)", led_r);

    // Test RED OFF ('r' = 0x72)
    rx_byte = 8'h72; rx_done = 1; #10; rx_done = 0; #10;
    $display("Sent 'r': led_r=%b (expect 0)", led_r);

    // Test GREEN ON ('G' = 0x47)
    rx_byte = 8'h47; rx_done = 1; #10; rx_done = 0; #10;
    $display("Sent 'G': led_g=%b (expect 1)", led_g);

    // Test GREEN OFF ('g' = 0x67)
    rx_byte = 8'h67; rx_done = 1; #10; rx_done = 0; #10;
    $display("Sent 'g': led_g=%b (expect 0)", led_g);

    // Test BLUE ON ('B' = 0x42)
    rx_byte = 8'h42; rx_done = 1; #10; rx_done = 0; #10;
    $display("Sent 'B': led_b=%b (expect 1)", led_b);

    // Test BLUE OFF ('b' = 0x62)
    rx_byte = 8'h62; rx_done = 1; #10; rx_done = 0; #10;
    $display("Sent 'b': led_b=%b (expect 0)", led_b);

    $display("===== Test Complete. Check led_controller.vcd =====");

    $finish;
  end

endmodule

UART_Actuator/led_controller_simulation/led_controller.vcd
$date
	Thu Jul 17 12:31:53 2025
$end
$version
	Icarus Verilog
$end
$timescale
	1ps
$end
$scope module led_controller_tb $end
$var wire 1 ! led_r $end
$var wire 1 " led_g $end
$var wire 1 # led_b $end
$var reg 1 $ clk $end
$var reg 8 % rx_byte [7:0] $end
$var reg 1 & rx_done $end
$scope module uut $end
$var wire 1 $ clk $end
$var wire 8 ' rx_byte [7:0] $end
$var wire 1 & rx_done $end
$var reg 1 # led_b $end
$var reg 1 " led_g $end
$var reg 1 ! led_r $end
$upscope $end
$upscope $end
$enddefinitions $end
$comment Show the parameter values. $end
$dumpall
$end
#0
$dumpvars
b0 '
0&
b0 %
0$
x#
x"
x!
$end
#5000
1$
#10000
0$
#15000
1$
#20000
0$
1&
b1010010 %
b1010010 '
#25000
1!
1$
#30000
0$
0&
#35000
1$
#40000
0$
1&
b1110010 %
b1110010 '
#45000
0!
1$
#50000
0$
0&
#55000
1$
#60000
0$
1&
b1000111 %
b1000111 '
#65000
1"
1$
#70000
0$
0&
#75000
1$
#80000
0$
1&
b1100111 %
b1100111 '
#85000
0"
1$
#90000
0$
0&
#95000
1$
#100000
0$
1&
b1000010 %
b1000010 '
#105000
1#
1$
#110000
0$
0&
#115000
1$
#120000
0$
1&
b1100010 %
b1100010 '
#125000
0#
1$
#130000
0$
0&
