UART_Actuator/uart_rx.v
module uart_rx (
    input clk,         // baud tick
    input rx,          // incoming serial data line
    output reg [7:0] rxbyte, // received byte
    output reg rxdone  // high for 1 clk when byte done
);

    // States
    parameter STATE_IDLE   = 2'd0;
    parameter STATE_RXING  = 2'd1;
    parameter STATE_DONE   = 2'd2;

    reg [1:0] state = STATE_IDLE;
    reg [7:0] rx_shift = 8'b0;
    reg [2:0] bit_count = 3'd0;

    always @(posedge clk) begin
        case (state)
            STATE_IDLE: begin
                rxdone <= 1'b0;
                if (rx == 1'b0) begin  // start bit detected (low)
                    state <= STATE_RXING;
                    bit_count <= 0;
                end
            end

            STATE_RXING: begin
                rx_shift <= {rx, rx_shift[7:1]}; // shift in LSB first
                bit_count <= bit_count + 1;
                if (bit_count == 7) begin
                    state <= STATE_DONE;
                end
            end

            STATE_DONE: begin
                rxbyte <= rx_shift;   // latch received byte
                rxdone <= 1'b1;       // pulse done flag
                state <= STATE_IDLE;  // back to idle to catch next byte
            end
        endcase
    end

endmodule

UART_Actuator/UART_RX_Simulation/uart_rx_tb.v
`timescale 1ns/1ps

module uart_rx_tb;
    reg clk = 0;
    reg rx = 1;
    wire [7:0] rxbyte;
    wire rxdone;

    uart_rx uut (
        .clk(clk),
        .rx(rx),
        .rxbyte(rxbyte),
        .rxdone(rxdone)
    );
  
    always #5 clk = ~clk;

    
    initial begin
        $dumpfile("uart_rx_tb.vcd");
        $dumpvars(0, uart_rx_tb);
    end

    
    task send_uart_byte(input [7:0] data);
        integer i;
        begin
            rx <= 0; 
            @(posedge clk);
            for (i = 0; i < 8; i = i + 1) begin
                rx <= data[i]; 
                @(posedge clk);
            end
            rx <= 1; 
            @(posedge clk);
        end
    endtask


    task test_char(input [7:0] send_char);
        reg [7:0] received_char;
        begin
            send_uart_byte(send_char);
            wait(rxdone == 1);
            received_char = rxbyte;
            @(posedge clk); 
            if (received_char == send_char)
                $display("send char = %c, received char = %c, pass", send_char, received_char);
            else
                $display("send char = %c, received char = %c, fail", send_char, received_char);
        end
    endtask

    initial begin
        $display("UART RX Testbench Begin");
        repeat (3) @(posedge clk);

        test_char("G"); 
        test_char("b"); 

        #20;
        $finish;
    end
endmodule

UART_Actuator/UART_RX_Simulation/uart_rx_tb.vcd
$date
	Thu Jul 17 16:55:57 2025
$end
$version
	Icarus Verilog
$end
$timescale
	1ps
$end
$scope module uart_rx_tb $end
$var wire 1 ! rxdone $end
$var wire 8 " rxbyte [7:0] $end
$var reg 1 # clk $end
$var reg 1 $ rx $end
$scope module uut $end
$var wire 1 # clk $end
$var wire 1 $ rx $end
$var parameter 2 % STATE_DONE $end
$var parameter 2 & STATE_IDLE $end
$var parameter 2 ' STATE_RXING $end
$var reg 3 ( bit_count [2:0] $end
$var reg 8 ) rx_shift [7:0] $end
$var reg 8 * rxbyte [7:0] $end
$var reg 1 ! rxdone $end
$var reg 2 + state [1:0] $end
$upscope $end
$scope task send_uart_byte $end
$var reg 8 , data [7:0] $end
$var integer 32 - i [31:0] $end
$upscope $end
$scope task test_char $end
$var reg 8 . received_char [7:0] $end
$var reg 8 / send_char [7:0] $end
$upscope $end
$upscope $end
$enddefinitions $end
$comment Show the parameter values. $end
$dumpall
b1 '
b0 &
b10 %
$end
#0
$dumpvars
bx /
bx .
bx -
bx ,
b0 +
bx *
b0 )
b0 (
1$
0#
bx "
x!
$end
#5000
0!
1#
#10000
0#
#15000
1#
#20000
0#
#25000
0$
b1000111 ,
b1000111 /
1#
#30000
0#
#35000
b1 +
1$
b0 -
1#
#40000
0#
#45000
b1 (
b10000000 )
b1 -
1#
#50000
0#
#55000
b10 (
b11000000 )
b10 -
1#
#60000
0#
#65000
0$
b11 (
b11100000 )
b11 -
1#
#70000
0#
#75000
b100 (
b1110000 )
b100 -
1#
#80000
0#
#85000
b101 (
b111000 )
b101 -
1#
#90000
0#
#95000
b110 (
b11100 )
1$
b110 -
1#
#100000
0#
#105000
0$
b111 (
b10001110 )
b111 -
1#
#110000
0#
#115000
b10 +
b0 (
b1000111 )
1$
b1000 -
1#
#120000
0#
#125000
b1000111 .
b0 +
1!
b1000111 "
b1000111 *
1#
#130000
0#
#135000
0$
0!
b1100010 ,
b1100010 /
1#
#140000
0#
#145000
b1 +
b0 -
1#
#150000
0#
#155000
1$
b1 (
b100011 )
b1 -
1#
#160000
0#
#165000
b10 (
b10010001 )
0$
b10 -
1#
#170000
0#
#175000
b11 (
b1001000 )
b11 -
1#
#180000
0#
#185000
b100 (
b100100 )
b100 -
1#
#190000
0#
#195000
1$
b101 (
b10010 )
b101 -
1#
#200000
0#
#205000
b110 (
b10001001 )
b110 -
1#
#210000
0#
#215000
0$
b111 (
b11000100 )
b111 -
1#
#220000
0#
#225000
b10 +
b0 (
b1100010 )
1$
b1000 -
1#
#230000
0#
#235000
b1100010 .
b0 +
1!
b1100010 "
b1100010 *
1#
#240000
0#
#245000
0!
1#
